<?xml version="1.0"?>
<session software="PathCore Session Printer" version="0.1.0">
    <image identifier="Y:\histology\CCSRI_Project\PostTreatment\ExtractedNucleiROIs\4_Region 15_crop.tif">
        <overlays>
            <graphic type="point" name="Region 16" description="IDC">
                <pen color="#005500ff" width="10" style="Solid"/>
                <font>MS Shell Dlg 2;8</font>
                <point-list>
                    <point>22,28</point>
                    <point>50,96</point>
                    <point>38,117</point>
                    <point>17,129</point>
                    <point>69,31</point>
                    <point>41,22</point>
                    <point>68,10</point>
                    <point>88,25</point>
                    <point>97,66</point>
                    <point>122,57</point>
                    <point>140,69</point>
                    <point>146,90</point>
                    <point>160,86</point>
                    <point>170,106</point>
                    <point>172,37</point>
                    <point>175,3</point>
                    <point>107,123</point>
                    <point>116,136</point>
                    <point>89,131</point>
                    <point>73,172</point>
                    <point>48,194</point>
                    <point>80,197</point>
                    <point>87,212</point>
                    <point>80,224</point>
                    <point>64,184</point>
                    <point>89,185</point>
                    <point>96,195</point>
                    <point>105,205</point>
                    <point>108,215</point>
                    <point>124,217</point>
                    <point>122,201</point>
                    <point>115,192</point>
                    <point>106,181</point>
                    <point>103,166</point>
                    <point>91,155</point>
                    <point>97,142</point>
                    <point>104,154</point>
                    <point>112,157</point>
                    <point>123,151</point>
                    <point>114,167</point>
                    <point>130,163</point>
                    <point>127,176</point>
                    <point>143,187</point>
                    <point>133,193</point>
                    <point>145,171</point>
                    <point>197,235</point>
                    <point>220,214</point>
                    <point>212,161</point>
                    <point>62,211</point>
                    <point>128,127</point>
                    <point>197,304</point>
                    <point>182,310</point>
                    <point>176,328</point>
                    <point>191,350</point>
                    <point>208,343</point>
                    <point>178,362</point>
                    <point>162,344</point>
                    <point>149,341</point>
                    <point>134,335</point>
                    <point>130,323</point>
                    <point>145,307</point>
                    <point>148,287</point>
                    <point>167,292</point>
                    <point>163,314</point>
                    <point>154,319</point>
                    <point>143,328</point>
                    <point>125,298</point>
                    <point>132,284</point>
                    <point>100,278</point>
                    <point>94,305</point>
                    <point>78,290</point>
                    <point>66,266</point>
                    <point>60,286</point>
                    <point>38,282</point>
                    <point>46,297</point>
                    <point>31,287</point>
                    <point>11,308</point>
                    <point>78,372</point>
                    <point>101,358</point>
                    <point>118,369</point>
                    <point>123,386</point>
                    <point>114,403</point>
                    <point>90,391</point>
                    <point>79,397</point>
                    <point>96,413</point>
                    <point>178,414</point>
                    <point>203,371</point>
                    <point>171,389</point>
                    <point>148,391</point>
                    <point>158,413</point>
                    <point>142,407</point>
                    <point>145,434</point>
                    <point>158,447</point>
                    <point>164,433</point>
                    <point>126,425</point>
                    <point>114,444</point>
                    <point>105,445</point>
                    <point>80,431</point>
                    <point>73,410</point>
                    <point>70,444</point>
                    <point>52,451</point>
                    <point>43,441</point>
                    <point>33,452</point>
                    <point>30,434</point>
                    <point>21,445</point>
                    <point>14,445</point>
                    <point>12,431</point>
                    <point>12,414</point>
                    <point>233,26</point>
                    <point>238,40</point>
                    <point>228,38</point>
                    <point>226,65</point>
                    <point>238,78</point>
                    <point>259,35</point>
                    <point>250,57</point>
                    <point>251,45</point>
                    <point>240,55</point>
                    <point>260,47</point>
                    <point>262,58</point>
                    <point>253,74</point>
                    <point>256,90</point>
                    <point>278,43</point>
                    <point>283,31</point>
                    <point>294,37</point>
                    <point>300,27</point>
                    <point>306,38</point>
                    <point>310,48</point>
                    <point>309,59</point>
                    <point>322,74</point>
                    <point>311,91</point>
                    <point>298,79</point>
                    <point>276,63</point>
                    <point>282,92</point>
                    <point>301,92</point>
                    <point>268,85</point>
                    <point>450,19</point>
                    <point>461,8</point>
                    <point>434,29</point>
                    <point>423,24</point>
                    <point>414,18</point>
                    <point>397,39</point>
                    <point>379,22</point>
                    <point>396,8</point>
                    <point>367,16</point>
                    <point>254,259</point>
                    <point>268,261</point>
                    <point>287,257</point>
                    <point>294,274</point>
                    <point>313,266</point>
                    <point>268,248</point>
                    <point>264,239</point>
                    <point>254,233</point>
                    <point>287,229</point>
                    <point>273,224</point>
                    <point>256,213</point>
                    <point>267,197</point>
                    <point>266,176</point>
                    <point>271,136</point>
                    <point>293,153</point>
                    <point>298,137</point>
                    <point>312,144</point>
                    <point>313,169</point>
                    <point>321,147</point>
                    <point>328,158</point>
                    <point>344,152</point>
                    <point>358,155</point>
                    <point>382,161</point>
                    <point>355,168</point>
                    <point>355,180</point>
                    <point>379,185</point>
                    <point>386,199</point>
                    <point>399,195</point>
                    <point>367,213</point>
                    <point>362,229</point>
                    <point>343,219</point>
                    <point>353,197</point>
                    <point>366,194</point>
                    <point>318,232</point>
                    <point>339,244</point>
                    <point>362,251</point>
                    <point>350,263</point>
                    <point>334,261</point>
                    <point>353,239</point>
                    <point>242,424</point>
                    <point>247,396</point>
                    <point>263,405</point>
                    <point>216,417</point>
                    <point>248,433</point>
                    <point>254,445</point>
                    <point>270,443</point>
                    <point>277,351</point>
                    <point>272,336</point>
                    <point>290,338</point>
                    <point>301,344</point>
                    <point>322,345</point>
                    <point>328,360</point>
                    <point>347,353</point>
                    <point>342,380</point>
                    <point>321,388</point>
                    <point>286,363</point>
                    <point>347,392</point>
                    <point>350,408</point>
                    <point>353,422</point>
                    <point>351,443</point>
                    <point>330,423</point>
                    <point>314,438</point>
                    <point>292,453</point>
                    <point>325,454</point>
                    <point>448,390</point>
                    <point>459,377</point>
                    <point>465,358</point>
                    <point>448,336</point>
                    <point>463,322</point>
                    <point>457,309</point>
                    <point>443,319</point>
                    <point>428,303</point>
                    <point>431,295</point>
                    <point>419,303</point>
                    <point>413,300</point>
                    <point>402,295</point>
                    <point>394,304</point>
                    <point>379,305</point>
                    <point>374,307</point>
                    <point>369,318</point>
                    <point>383,320</point>
                    <point>387,343</point>
                    <point>398,348</point>
                    <point>424,340</point>
                    <point>431,353</point>
                    <point>414,359</point>
                    <point>413,370</point>
                    <point>410,388</point>
                    <point>399,370</point>
                    <point>430,402</point>
                    <point>439,378</point>
                    <point>487,74</point>
                    <point>468,83</point>
                    <point>483,96</point>
                    <point>457,117</point>
                    <point>455,93</point>
                    <point>430,91</point>
                    <point>435,78</point>
                    <point>399,87</point>
                    <point>416,107</point>
                    <point>402,121</point>
                    <point>380,121</point>
                    <point>440,128</point>
                    <point>432,116</point>
                    <point>464,130</point>
                    <point>480,150</point>
                    <point>460,172</point>
                    <point>472,195</point>
                    <point>479,179</point>
                    <point>459,205</point>
                    <point>478,211</point>
                    <point>442,194</point>
                    <point>422,187</point>
                    <point>557,94</point>
                    <point>529,84</point>
                    <point>558,63</point>
                    <point>568,22</point>
                    <point>622,125</point>
                    <point>616,137</point>
                    <point>614,126</point>
                    <point>596,114</point>
                    <point>579,116</point>
                    <point>561,118</point>
                    <point>553,134</point>
                    <point>556,156</point>
                    <point>548,172</point>
                    <point>538,192</point>
                    <point>553,200</point>
                    <point>568,204</point>
                    <point>617,182</point>
                    <point>633,167</point>
                    <point>602,153</point>
                    <point>610,170</point>
                    <point>594,181</point>
                    <point>641,277</point>
                    <point>627,249</point>
                    <point>617,235</point>
                    <point>597,244</point>
                    <point>579,232</point>
                    <point>562,243</point>
                    <point>550,261</point>
                    <point>567,277</point>
                    <point>572,261</point>
                    <point>573,299</point>
                    <point>578,315</point>
                    <point>592,324</point>
                    <point>602,343</point>
                    <point>620,311</point>
                    <point>618,297</point>
                    <point>634,292</point>
                    <point>655,287</point>
                    <point>666,39</point>
                    <point>668,15</point>
                    <point>633,40</point>
                    <point>586,431</point>
                    <point>681,439</point>
                    <point>649,451</point>
                    <point>683,388</point>
                    <point>682,358</point>
                    <point>666,383</point>
                    <point>649,388</point>
                    <point>694,243</point>
                    <point>671,73</point>
                    <point>693,59</point>
                    <point>672,100</point>
                    <point>693,17</point>
                    <point>497,145</point>
                    <point>501,306</point>
                    <point>191,194</point>
                </point-list>
            </graphic>
            <graphic type="point" name="Region 17" description="TIL-E">
                <pen color="#00ff7fff" width="10" style="Solid"/>
                <font>MS Shell Dlg 2;8</font>
                <point-list>
                    <point>190,437</point>
                    <point>649,211</point>
                    <point>222,340</point>
                    <point>520,200</point>
                    <point>534,215</point>
                    <point>241,296</point>
                </point-list>
            </graphic>
            <graphic type="point" name="Region 18" description="IDC">
                <pen color="#005500ff" width="10" style="Solid"/>
                <font>MS Shell Dlg 2;8</font>
                <point-list>
                    <point>635,405</point>
                    <point>629,395</point>
                    <point>642,18</point>
                    <point>279,371</point>
                    <point>261,394</point>
                    <point>638,307</point>
                    <point>692,125</point>
                    <point>577,47</point>
                    <point>601,43</point>
                    <point>557,188</point>
                    <point>570,173</point>
                    <point>686,211</point>
                    <point>288,426</point>
                    <point>330,367</point>
                    <point>303,375</point>
                </point-list>
            </graphic>
        </overlays>
</session>