<?xml version="1.0"?>
<session software="PathCore Session Printer" version="0.1.0">
<image identifier="121_Region 19_crop.tif">
<dimensions>402,402</dimensions>
<pixel-size units="um">1.000000,1.000000</pixel-size>
        <overlays>
            <graphic type="point" name="Region 20" description="normal">
<attributes/>
                <pen color="#ff0000ff" width="10" style="Solid"/>
                <font>MS Shell Dlg 2;8</font>
                <point-list>
                    <point>147,299</point>
                    <point>160,342</point>
                    <point>145,331</point>
                    <point>136,337</point>
                    <point>143,356</point>
                    <point>129,356</point>
                    <point>121,365</point>
                    <point>106,373</point>
                    <point>103,353</point>
                    <point>91,359</point>
                    <point>110,322</point>
                    <point>103,306</point>
                    <point>99,322</point>
                    <point>95,314</point>
                    <point>143,281</point>
                    <point>137,269</point>
                    <point>130,255</point>
                    <point>118,268</point>
                    <point>115,292</point>
                    <point>272,356</point>
                    <point>278,337</point>
                    <point>290,345</point>
                    <point>286,358</point>
                    <point>259,354</point>
                    <point>229,270</point>
                    <point>213,268</point>
                    <point>207,250</point>
                    <point>211,230</point>
                    <point>209,212</point>
                    <point>198,189</point>
                    <point>207,178</point>
                    <point>213,166</point>
                    <point>223,173</point>
                    <point>247,177</point>
                    <point>260,191</point>
                    <point>273,202</point>
                    <point>280,209</point>
                    <point>294,236</point>
                    <point>259,242</point>
                    <point>251,259</point>
                    <point>263,255</point>
                    <point>279,263</point>
                    <point>300,278</point>
                    <point>295,263</point>
                    <point>285,285</point>
                    <point>285,301</point>
                    <point>318,284</point>
                    <point>312,266</point>
                    <point>345,265</point>
                    <point>336,255</point>
                    <point>326,243</point>
                    <point>326,234</point>
                    <point>338,231</point>
                    <point>318,218</point>
                    <point>294,211</point>
                    <point>297,202</point>
                    <point>138,21</point>
                    <point>152,38</point>
                    <point>113,32</point>
                    <point>44,52</point>
                    <point>48,73</point>
                    <point>65,57</point>
                    <point>58,150</point>
                    <point>42,156</point>
                    <point>41,184</point>
                    <point>58,180</point>
                    <point>52,194</point>
                    <point>34,202</point>
                    <point>87,204</point>
                    <point>74,184</point>
                    <point>376,343</point>
                    <point>362,343</point>
                    <point>360,331</point>
                    <point>345,331</point>
                    <point>342,315</point>
                    <point>358,305</point>
                    <point>383,300</point>
                    <point>392,349</point>
                    <point>409,297</point>
                    <point>423,312</point>
                    <point>431,333</point>
                    <point>418,340</point>
                    <point>417,351</point>
                    <point>441,321</point>
                    <point>471,240</point>
                    <point>457,239</point>
                    <point>441,232</point>
                    <point>433,232</point>
                    <point>414,195</point>
                    <point>409,210</point>
                    <point>398,179</point>
                    <point>384,184</point>
                    <point>359,190</point>
                    <point>346,190</point>
                    <point>330,183</point>
                    <point>320,177</point>
                    <point>314,164</point>
                    <point>309,150</point>
                    <point>297,122</point>
                    <point>308,132</point>
                    <point>336,122</point>
                    <point>352,111</point>
                    <point>489,210</point>
                    <point>501,208</point>
                    <point>497,195</point>
                    <point>504,175</point>
                    <point>494,150</point>
                    <point>477,146</point>
                    <point>468,132</point>
                    <point>458,122</point>
                    <point>445,123</point>
                    <point>433,116</point>
                    <point>427,111</point>
                    <point>413,108</point>
                    <point>425,81</point>
                    <point>435,70</point>
                    <point>424,57</point>
                    <point>407,54</point>
                    <point>381,50</point>
                    <point>394,78</point>
                    <point>394,94</point>
                    <point>384,91</point>
                    <point>366,93</point>
                    <point>374,69</point>
                    <point>371,56</point>
                    <point>293,25</point>
                    <point>283,18</point>
                    <point>270,6</point>
                    <point>269,18</point>
                    <point>258,26</point>
                    <point>268,33</point>
                    <point>271,48</point>
                    <point>285,52</point>
                    <point>302,54</point>
                    <point>331,62</point>
                    <point>314,20</point>
                    <point>305,31</point>
                    <point>319,8</point>
                    <point>327,20</point>
                    <point>334,16</point>
                    <point>320,103</point>
                    <point>347,80</point>
                    <point>505,376</point>
                    <point>495,367</point>
                    <point>502,387</point>
                    <point>488,398</point>
                    <point>434,393</point>
                    <point>412,394</point>
                    <point>474,372</point>
                </point-list>
            </graphic>
        </overlays>
</image>
</session>